wati_api/__init__.py
wati_api/client.py
wati_api/exceptions.py
wati_api/http.py
wati_api/utils.py
wati_api/version.py
wati_api-0.2.2.dist-info/AUTHORS
wati_api-0.2.2.dist-info/LICENSE
wati_api-0.2.2.dist-info/METADATA
wati_api-0.2.2.dist-info/WHEEL
wati_api-0.2.2.dist-info/pbr.json
wati_api-0.2.2.dist-info/top_level.txt
wati_api-0.2.2.dist-info/RECORD
